max30105/__init__.py
max30105-0.0.5.dist-info/LICENSE.txt
max30105-0.0.5.dist-info/METADATA
max30105-0.0.5.dist-info/WHEEL
max30105-0.0.5.dist-info/top_level.txt
max30105-0.0.5.dist-info/RECORD
